{
  "id": "DG-0343",
  "title": "蜡烛使用边界",
  "category": "能源照明与设备",
  "scenario": "电量不足时考虑使用蜡烛照明。",
  "goal": "降低火灾、烫伤和夜间复燃风险。",
  "tools": [
    "蜡烛",
    "稳定底座",
    "金属盘",
    "水或沙土",
    "记录本"
  ],
  "steps": [
    "蜡烛只放在稳定、耐热、不可燃底座上。",
    "周围清理纸张、布料、塑料、燃料和头发容易碰到的位置。",
    "蜡烛不放床边、地面、窗帘旁和儿童可碰位置。",
    "有人看守时才点蜡烛，睡觉前必须熄灭。",
    "蜡烛移动前先熄灭，不端着明火穿过拥挤空间。",
    "旁边准备水、沙土或金属盖。",
    "熄灭后确认烛芯没有复燃或冒烟。"
  ],
  "check": [
    "蜡烛底座稳定。",
    "周围无易燃物。",
    "睡前已熄灭。"
  ],
  "common_mistakes": [
    "蜡烛放纸盒上。",
    "点着蜡烛睡觉。",
    "端着蜡烛找东西。"
  ],
  "fallback": "如果环境拥挤、儿童多或有风，优先不用蜡烛，改用低亮电灯。",
  "stop_or_escalate": [
    "蜡烛倾倒、火苗靠近布料、无人看守、睡意明显时，立即熄灭。"
  ],
  "notes": "蜡烛不是浪漫，是一根小型火源。",
  "category_original": "照明与夜间行动",
  "domains": [
    "power",
    "security"
  ],
  "intents": [
    "power_lighting_energy"
  ],
  "situations": [
    "scarcity",
    "night"
  ],
  "objects": [
    "battery",
    "lighting"
  ],
  "keywords": [
    "蜡烛使用边界",
    "电量",
    "照明",
    "设备",
    "夜间",
    "风险",
    "scarcity",
    "night",
    "battery",
    "lighting",
    "power_lighting_energy",
    "能源照明"
  ],
  "negative_keywords": [
    "腹泻",
    "发热",
    "伤口",
    "主食配给",
    "夜间异响",
    "主食",
    "剩饭",
    "冰箱食物",
    "罐头鼓包"
  ]
}