{
  "id": "DG-0367",
  "title": "通风路径设计",
  "category": "灾害应对与灾后恢复",
  "priority": "P0",
  "scenario": "室内闷热、潮湿、烟味、厕所气味、多人共处或做饭后空气差。",
  "goal": "设计可控通风，让空气流动但不暴露和不引入危险。",
  "tools": [
    "布条风向标",
    "窗帘",
    "门挡",
    "记录本"
  ],
  "steps": [
    "先判断外部空气是否安全，有浓烟、化学味、粉尘时不直接通风。",
    "找出进风口和出风口，形成空气流动。",
    "厕所、垃圾、厨房气味不要吹向睡眠和饮食区。",
    "用布条观察风向，避免把污染气味吹进核心区。",
    "白天或安全时段短时通风，寒冷时分段通风。",
    "通风时注意窗外视线和光痕，不暴露内部布局。",
    "每天记录最有效的通风组合。"
  ],
  "check": [
    "有进风和出风。",
    "污染气味不吹向睡眠区。",
    "外部空气安全时才通风。"
  ],
  "common_mistakes": [
    "外面有烟还开窗。",
    "厕所风吹向厨房。",
    "通风暴露内部物资。"
  ],
  "fallback": "无法开窗时，用门缝、楼道、风扇或手动扇风做短时换气。",
  "stop_or_escalate": [
    "多人头晕、燃烧废气、化学味、烟味进入室内时，立即改变通风或撤离。"
  ],
  "notes": "空气也有路线，路线错了，气味会排队进屋。",
  "category_original": "室内空气管理",
  "domains": [
    "disaster",
    "security",
    "shelter",
    "hygiene",
    "medical"
  ],
  "intents": [
    "hygiene_contamination"
  ],
  "situations": [
    "resource_exposure"
  ],
  "objects": [
    "toilet",
    "route"
  ],
  "keywords": [
    "通风路径设计",
    "厕所",
    "resource_exposure",
    "toilet",
    "route",
    "hygiene_contamination",
    "灾害应对",
    "灾后恢复"
  ],
  "negative_keywords": [
    "主食",
    "剩饭",
    "冰箱食物",
    "罐头鼓包",
    "夜间异响",
    "太阳能充电",
    "主食配给"
  ]
}
