{
  "id": "DG-0102",
  "title": "婴儿冲奶用水安全",
  "category": "医疗急救与照护",
  "priority": "P0",
  "scenario": "需要给婴儿冲奶、辅食或清洗奶瓶，但水源紧张。",
  "goal": "优先保护婴儿入口用品和用水安全。",
  "tools": [
    "安全水",
    "奶瓶",
    "清洁刷",
    "锅",
    "干净布"
  ],
  "steps": [
    "婴儿入口用水优先使用已处理的安全水。",
    "奶瓶、奶嘴、勺子和入口用品单独清洗。",
    "冲调前洗手，台面尽量清洁。",
    "按奶粉说明冲调，不随意加浓或加稀。",
    "冲好后尽快喂完，剩奶不要长时间保存。",
    "无法保证清洁时，优先减少奶瓶污染，使用后立即清洗晾干。"
  ],
  "check": [
    "冲奶水来源明确。",
    "奶瓶入口部位干净。",
    "剩奶没有留到下一顿。"
  ],
  "common_mistakes": [
    "用来源不明水冲奶。",
    "奶瓶放在污染台面。",
    "把剩奶反复加热。"
  ],
  "fallback": "没有奶瓶刷时，用干净布条和热水尽量清洁瓶内，但要特别注意晾干。",
  "stop_or_escalate": [
    "婴儿腹泻、呕吐、发热、尿量减少、精神差。"
  ],
  "notes": "婴儿用水优先级高于普通清洁用水。",
  "category_original": "特殊人群",
  "domains": [
    "medical",
    "security",
    "water"
  ],
  "intents": [
    "water_rationing"
  ],
  "situations": [],
  "objects": [
    "drinking_water"
  ],
  "keywords": [
    "婴儿冲奶用水安全",
    "安全",
    "水源",
    "drinking_water",
    "water_rationing",
    "医疗急救",
    "照护"
  ],
  "negative_keywords": [
    "主食配给",
    "冰箱食物",
    "太阳能充电",
    "夜间异响",
    "主食",
    "剩饭",
    "罐头鼓包",
    "异响",
    "脚步声",
    "门外"
  ]
}
